{
  "batchInfo": {
    "batchNumber": 468,
    "startIndex": 1401,
    "urlCount": 3,
    "timestamp": "2025-06-06T11-25-10-679Z"
  },
  "results": [
    {
      "success": false,
      "url": "https://ehliyetsinavihazirlik.com/index.php/e-sinav-nisan-17.html",
      "error": "AI processing failed: API Error: 429 Too Many Requests",
      "cost": 0
    },
    {
      "success": false,
      "url": "https://ehliyetsinavihazirlik.com/index.php/e-sinav-nisan-3.html",
      "error": "AI processing failed: API Error: 401 Unauthorized",
      "cost": 0
    },
    {
      "success": false,
      "url": "https://ehliyetsinavihazirlik.com/index.php/e-sinav-nisan-18.html",
      "error": "AI processing failed: API Error: 401 Unauthorized",
      "cost": 0
    }
  ]
}