{
  "batchInfo": {
    "batchNumber": 564,
    "startIndex": 1689,
    "urlCount": 3,
    "timestamp": "2025-06-06T11-46-34-644Z"
  },
  "results": [
    {
      "success": false,
      "url": "https://ehliyetsinavihazirlik.com/index.php/e-ehliyet-sinavi-10.html",
      "error": "AI processing failed: API Error: 429 Too Many Requests",
      "cost": 0
    },
    {
      "success": false,
      "url": "https://ehliyetsinavihazirlik.com/index.php/e-ehliyet-sinavi-25.html",
      "error": "AI processing failed: API Error: 429 Too Many Requests",
      "cost": 0
    },
    {
      "success": false,
      "url": "https://ehliyetsinavihazirlik.com/index.php/e-ehliyet-sinavi-11.html",
      "error": "AI processing failed: API Error: 429 Too Many Requests",
      "cost": 0
    }
  ]
}