{
  "batchInfo": {
    "batchNumber": 11,
    "startIndex": 30,
    "urlCount": 3,
    "timestamp": "2025-06-06T09-41-27-242Z"
  },
  "results": [
    {
      "success": false,
      "url": "https://ehliyetsinavihazirlik.com/index.php/e-sinavlar-mayis-sorulari-1.html",
      "error": "AI processing failed: API Error: 429 Too Many Requests",
      "cost": 0
    },
    {
      "success": false,
      "url": "https://ehliyetsinavihazirlik.com/index.php/e-sinavlar-mayis-sorulari-17.html",
      "error": "AI processing failed: API Error: 401 Unauthorized",
      "cost": 0
    },
    {
      "success": false,
      "url": "https://ehliyetsinavihazirlik.com/index.php/e-sinavlar-mayis-sorulari-2.html",
      "error": "AI processing failed: API Error: 429 Too Many Requests",
      "cost": 0
    }
  ]
}